inspect_ai/__init__.py
inspect_ai/__main__.py
inspect_ai/py.typed
inspect_ai/_cli/cache.py
inspect_ai/_cli/common.py
inspect_ai/_cli/eval.py
inspect_ai/_cli/info.py
inspect_ai/_cli/list.py
inspect_ai/_cli/log.py
inspect_ai/_cli/main.py
inspect_ai/_cli/sandbox.py
inspect_ai/_cli/score.py
inspect_ai/_cli/trace.py
inspect_ai/_cli/util.py
inspect_ai/_cli/view.py
inspect_ai/_display/__init__.py
inspect_ai/_display/core/active.py
inspect_ai/_display/core/config.py
inspect_ai/_display/core/display.py
inspect_ai/_display/core/footer.py
inspect_ai/_display/core/panel.py
inspect_ai/_display/core/progress.py
inspect_ai/_display/core/results.py
inspect_ai/_display/core/rich.py
inspect_ai/_display/core/textual.py
inspect_ai/_display/log/__init__.py
inspect_ai/_display/log/display.py
inspect_ai/_display/plain/__init__.py
inspect_ai/_display/plain/display.py
inspect_ai/_display/rich/__init__.py
inspect_ai/_display/rich/display.py
inspect_ai/_display/textual/app.py
inspect_ai/_display/textual/app.tcss
inspect_ai/_display/textual/display.py
inspect_ai/_display/textual/theme.py
inspect_ai/_display/textual/widgets/clock.py
inspect_ai/_display/textual/widgets/console.py
inspect_ai/_display/textual/widgets/footer.py
inspect_ai/_display/textual/widgets/port_mappings.py
inspect_ai/_display/textual/widgets/samples.py
inspect_ai/_display/textual/widgets/sandbox.py
inspect_ai/_display/textual/widgets/task_detail.py
inspect_ai/_display/textual/widgets/tasks.py
inspect_ai/_display/textual/widgets/titlebar.py
inspect_ai/_display/textual/widgets/toggle.py
inspect_ai/_display/textual/widgets/transcript.py
inspect_ai/_display/textual/widgets/vscode.py
inspect_ai/_eval/__init__.py
inspect_ai/_eval/context.py
inspect_ai/_eval/eval.py
inspect_ai/_eval/evalset.py
inspect_ai/_eval/list.py
inspect_ai/_eval/loader.py
inspect_ai/_eval/registry.py
inspect_ai/_eval/run.py
inspect_ai/_eval/score.py
inspect_ai/_eval/task/__init__.py
inspect_ai/_eval/task/constants.py
inspect_ai/_eval/task/epochs.py
inspect_ai-0.3.169.dist-info/licenses/LICENSE
inspect_ai-0.3.169.dist-info/METADATA
inspect_ai-0.3.169.dist-info/WHEEL
inspect_ai-0.3.169.dist-info/entry_points.txt
inspect_ai-0.3.169.dist-info/top_level.txt
inspect_ai-0.3.169.dist-info/RECORD
